<?xml version="1.0" encoding="UTF-8"?>
<databaseChangeLog 
	xmlns="http://www.liquibase.org/xml/ns/dbchangelog" 
	xmlns:xsi="http://www.w3.org/2001/XMLSchema-instance" 
	xmlns:n0="http://www.oracle.com/xml/ns/dbchangelog-ext" 
	xsi:schemaLocation="http://www.liquibase.org/xml/ns/dbchangelog 
	http://www.liquibase.org/xml/ns/dbchangelog/dbchangelog-latest.xsd">
	<changeSet id="6ff2724d646a43c54a8a6e179e7f1c4c36ef0009" author="(HR)-Generated" failOnError="false"   runOnChange="true" runAlways="false"  >
		<n0:createSxmlObject objectName="CUSTOMER_MIS" objectType="TABLE" ownerName="HR"  replaceIfExists="true" >
			<n0:source><![CDATA[
  <TABLE xmlns="http://xmlns.oracle.com/ku" version="1.0">
   <SCHEMA>HR</SCHEMA>
   <NAME>CUSTOMER_MIS</NAME>
   <RELATIONAL_TABLE>
      <COL_LIST>
         <COL_LIST_ITEM>
            <NAME>ISN</NAME>
            <DATATYPE>NUMBER</DATATYPE>
            <PRECISION>16</PRECISION>
            <SCALE>0</SCALE>
            <IDENTITY_COLUMN>
               <SCHEMA>HR</SCHEMA>
               <GENERATION>ALWAYS</GENERATION>
               <START_WITH>1</START_WITH>
               <INCREMENT>1</INCREMENT>
               <MINVALUE>1</MINVALUE>
               <MAXVALUE>9999999999999999999999999999</MAXVALUE>
               <CACHE>20</CACHE>
            </IDENTITY_COLUMN>
            <NOT_NULL></NOT_NULL>
         </COL_LIST_ITEM>
         <COL_LIST_ITEM>
            <NAME>CUSTOMER_ISN</NAME>
            <DATATYPE>NUMBER</DATATYPE>
            <PRECISION>16</PRECISION>
            <SCALE>0</SCALE>
            <NOT_NULL></NOT_NULL>
         </COL_LIST_ITEM>
         <COL_LIST_ITEM>
            <NAME>MIS_SUBCODE_ISN</NAME>
            <DATATYPE>NUMBER</DATATYPE>
            <PRECISION>4</PRECISION>
            <SCALE>0</SCALE>
         </COL_LIST_ITEM>
         <COL_LIST_ITEM>
            <NAME>CREATED_BY</NAME>
            <DATATYPE>NUMBER</DATATYPE>
            <PRECISION>6</PRECISION>
            <SCALE>0</SCALE>
         </COL_LIST_ITEM>
         <COL_LIST_ITEM>
            <NAME>CREATED_ON</NAME>
            <DATATYPE>TIMESTAMP</DATATYPE>
            <SCALE>6</SCALE>
            <DEFAULT>sysdate</DEFAULT>
         </COL_LIST_ITEM>
         <COL_LIST_ITEM>
            <NAME>UPDATED_BY</NAME>
            <DATATYPE>NUMBER</DATATYPE>
            <PRECISION>6</PRECISION>
            <SCALE>0</SCALE>
         </COL_LIST_ITEM>
         <COL_LIST_ITEM>
            <NAME>UPDATED_ON</NAME>
            <DATATYPE>TIMESTAMP</DATATYPE>
            <SCALE>6</SCALE>
         </COL_LIST_ITEM>
      </COL_LIST>
      <PRIMARY_KEY_CONSTRAINT_LIST>
         <PRIMARY_KEY_CONSTRAINT_LIST_ITEM>
            <NAME>CUMI_PK</NAME>
            <COL_LIST>
               <COL_LIST_ITEM>
                  <NAME>ISN</NAME>
               </COL_LIST_ITEM>
            </COL_LIST>
            <USING_INDEX>
               <INDEX_ATTRIBUTES>
                  <PCTFREE>10</PCTFREE>
                  <INITRANS>2</INITRANS>
                  <MAXTRANS>255</MAXTRANS>
                  <TABLESPACE>SYSAUX</TABLESPACE>
                  <LOGGING>Y</LOGGING>
               </INDEX_ATTRIBUTES>
            </USING_INDEX>
         </PRIMARY_KEY_CONSTRAINT_LIST_ITEM>
      </PRIMARY_KEY_CONSTRAINT_LIST>
      <UNIQUE_KEY_CONSTRAINT_LIST>
         <UNIQUE_KEY_CONSTRAINT_LIST_ITEM>
            <NAME>CUMI_UK1</NAME>
            <COL_LIST>
               <COL_LIST_ITEM>
                  <NAME>CUSTOMER_ISN</NAME>
               </COL_LIST_ITEM>
               <COL_LIST_ITEM>
                  <NAME>MIS_SUBCODE_ISN</NAME>
               </COL_LIST_ITEM>
            </COL_LIST>
            <USING_INDEX>
               <INDEX_ATTRIBUTES>
                  <PCTFREE>10</PCTFREE>
                  <INITRANS>2</INITRANS>
                  <MAXTRANS>255</MAXTRANS>
                  <TABLESPACE>SYSAUX</TABLESPACE>
                  <LOGGING>Y</LOGGING>
               </INDEX_ATTRIBUTES>
            </USING_INDEX>
         </UNIQUE_KEY_CONSTRAINT_LIST_ITEM>
      </UNIQUE_KEY_CONSTRAINT_LIST>
      <DEFAULT_COLLATION>USING_NLS_COMP</DEFAULT_COLLATION>
      <PHYSICAL_PROPERTIES>
         <HEAP_TABLE>
            <SEGMENT_ATTRIBUTES>
               <SEGMENT_CREATION_DEFERRED></SEGMENT_CREATION_DEFERRED>
               <PCTFREE>10</PCTFREE>
               <PCTUSED>40</PCTUSED>
               <INITRANS>1</INITRANS>
               <MAXTRANS>255</MAXTRANS>
               <TABLESPACE>SYSAUX</TABLESPACE>
               <LOGGING>Y</LOGGING>
            </SEGMENT_ATTRIBUTES>
            <COMPRESS>N</COMPRESS>
         </HEAP_TABLE>
      </PHYSICAL_PROPERTIES>
   </RELATIONAL_TABLE>
</TABLE>]]></n0:source>
		</n0:createSxmlObject>
	</changeSet>
</databaseChangeLog>
